fitting/__init__.py
fitting/plotting.py
FPfits-0.0.3.dist-info/METADATA
FPfits-0.0.3.dist-info/WHEEL
FPfits-0.0.3.dist-info/top_level.txt
FPfits-0.0.3.dist-info/RECORD
